{
    "timestamp": "2026-07-18T04:45:00+00:00",
    "difficulty": {
        "2": 2,
        "1": 1
    },
    "mode": {
        "1": 1,
        "0": 2
    },
    "activities": [
        {
            "name": "Other",
            "count": 3
        }
    ],
    "top_games": [
        {
            "name": "a",
            "count": 2
        },
        {
            "name": "trapper jim 1",
            "count": 1
        }
    ],
    "unknown_games": [
        {
            "normalized": "a",
            "count": 4,
            "examples": [
                "a"
            ]
        },
        {
            "normalized": "trapper jim #",
            "count": 2,
            "examples": [
                "trapper jim 1"
            ]
        }
    ],
    "classified_games": {},
    "interesting": {
        "unique_names": 2,
        "public_games": 3,
        "average_name_length": 7.0
    }
}