{
    "timestamp": "2026-07-19T20:16:00+00:00",
    "difficulty": {
        "2": 3,
        "0": 1
    },
    "mode": {
        "0": 4
    },
    "difficulty_mode": {
        "2|0": 3,
        "0|0": 1
    },
    "activities": [
        {
            "name": "Chaos",
            "count": 1
        },
        {
            "name": "Misc. Public MF Runs",
            "count": 1
        },
        {
            "name": "Trade",
            "count": 1
        },
        {
            "name": "Leveling",
            "count": 1
        }
    ],
    "top_games": [
        {
            "name": "i dia u 01",
            "count": 1
        },
        {
            "name": "asdasdas",
            "count": 1
        },
        {
            "name": "1 ooc for 1 eld",
            "count": 1
        },
        {
            "name": "norm levelin",
            "count": 1
        }
    ],
    "unknown_games": [],
    "classified_games": {
        "Chaos": [
            {
                "name": "i dia u 01",
                "matched": "dia",
                "count": 1
            }
        ],
        "Misc. Public MF Runs": [
            {
                "name": "asdasdas",
                "matched": "asd",
                "count": 1
            }
        ],
        "Trade": [
            {
                "name": "1 ooc for 1 eld",
                "matched": "for",
                "count": 1
            }
        ],
        "Leveling": [
            {
                "name": "norm levelin",
                "matched": "norm",
                "count": 1
            }
        ]
    },
    "interesting": {
        "unique_names": 4,
        "public_games": 4,
        "average_name_length": 11.25
    }
}