{
    "timestamp": "2026-07-12T18:17:00+00:00",
    "difficulty": {
        "1": 2,
        "0": 3
    },
    "mode": {
        "1": 4,
        "0": 1
    },
    "activities": [
        {
            "name": "Other",
            "count": 5
        }
    ],
    "top_games": [
        {
            "name": "qordsohandsome",
            "count": 1
        },
        {
            "name": "cain",
            "count": 1
        },
        {
            "name": "a",
            "count": 1
        },
        {
            "name": "ok",
            "count": 1
        },
        {
            "name": "help",
            "count": 1
        }
    ],
    "unknown_games": [
        {
            "normalized": "qordsohandsome",
            "count": 2,
            "examples": [
                "qordsohandsome"
            ]
        },
        {
            "normalized": "cain",
            "count": 2,
            "examples": [
                "cain"
            ]
        },
        {
            "normalized": "a",
            "count": 2,
            "examples": [
                "a"
            ]
        },
        {
            "normalized": "ok",
            "count": 2,
            "examples": [
                "ok"
            ]
        },
        {
            "normalized": "help",
            "count": 2,
            "examples": [
                "help"
            ]
        }
    ],
    "classified_games": {},
    "interesting": {
        "unique_names": 5,
        "public_games": 5,
        "average_name_length": 5.0
    }
}