{
    "timestamp": "2026-07-06T01:55:00+00:00",
    "difficulty": {
        "0": 1,
        "2": 3
    },
    "mode": {
        "1": 1,
        "0": 3
    },
    "activities": [
        {
            "name": "Other",
            "count": 3
        },
        {
            "name": "Leveling",
            "count": 1
        }
    ],
    "top_games": [
        {
            "name": "a3",
            "count": 1
        },
        {
            "name": "nico1",
            "count": 1
        },
        {
            "name": "nico",
            "count": 1
        },
        {
            "name": "qetqt",
            "count": 1
        }
    ],
    "interesting": {
        "unique_names": 4,
        "public_games": 4,
        "average_name_length": 4.0
    }
}