{
    "timestamp": "2026-07-23T23:18:00+00:00",
    "difficulty": {
        "0": 2
    },
    "mode": {
        "1": 1,
        "0": 1
    },
    "difficulty_mode": {
        "0|1": 1,
        "0|0": 1
    },
    "activities": [
        {
            "name": "Leveling",
            "count": 2
        }
    ],
    "top_games": [
        {
            "name": "ancients norm",
            "count": 1
        },
        {
            "name": "act",
            "count": 1
        }
    ],
    "unknown_games": [],
    "classified_games": {
        "Leveling": [
            {
                "name": "ancients norm",
                "matched": "norm",
                "count": 1
            },
            {
                "name": "act",
                "matched": "act",
                "count": 1
            }
        ]
    },
    "interesting": {
        "unique_names": 2,
        "public_games": 2,
        "average_name_length": 8.0
    }
}